Workbook

Sheet Start here
B2: 127 · BUILD TRACK · BUILDER
B3: Launch Countdown
B4: Every step from picking a launch date to the week after launch, with a do-by date for each so nothing important gets missed.
B6: HOW TO USE IT
B7: 1. Open the Setup tab and type your launch date. Pick a day about 14 days out.
B8: 2. Every task in the Countdown tab gets its do-by date from that one cell.
B9: 3. Mark each task To do, Doing or Done. Overdue tasks turn red, tasks due in two days turn yellow.
B10: 4. The Setup tab shows your progress and the next task due.
B11: 5. Launch week: do the day's tasks, log every reply in the Pipeline Tracker and every objection in the Objection Log.
B13: CELL COLORS
B14: White cells: you type here.
B15: Grey cells: calculated for you. Leave them alone.
... B26: Template drafted from Eli Christiansen's frameworks. © 127 Group LLC. For your own business use.

Sheet Setup
A1: Launch Countdown
A2: Type your launch date. Everything else fills in.
A4: YOUR LAUNCH
A5: Launch day
A6: Days until launch | B6: =IF($B$5="","",$B$5-TODAY())
A7: The three people checking in on you
A9: PROGRESS
A10: Tasks | B10: =COUNTA('Countdown'!$C$4:$C$45)
A11: Done | B11: =COUNTIF('Countdown'!$G$4:$G$45,"Done")
A12: Percent done | B12: =IF(B10=0,"",B11/B10)
A13: Overdue | B13: =COUNTIFS('Countdown'!$F$4:$F$45,"<0")
A14: Next task due | B14: =IF(COUNT('Countdown'!$K$4:$K$45)=0,"",INDEX('Countdown'!$C$4:$C$45,MATCH(MIN('Countdown'!$K$4:$K$45),'Countdown'!$K$4:$K$45,0)))
A15: Its do-by date | B15: =IF(COUNT('Countdown'!$K$4:$K$45)=0,"",MIN('Countdown'!$K$4:$K$45))

Sheet Countdown
A1: Launch Countdown
A2: Do-by dates come from your launch date on the Setup tab.
A3: # | B3: Phase | C3: Task | D3: Days from launch | E3: Do by | F3: Days left | G3: Status | H3: Done on | I3: Notes | J3: id | K3: open
A4: 1 | B4: Today | C4: Pick a launch date about 14 days out and put it on your calendar. | D4: -14 | E4: =IF('Setup'!$B$5="","",'Setup'!$B$5+D4) | F4: =IF(OR(E4="",G4="Done"),"",E4-TODAY()) | J4: launch-countdown.today.1 | K4: =IF(OR(G4="Done",G4="Skipped"),"",E4)
A5: 2 | B5: Today | C5: Text three people the date and ask them to check in on you. | D5: -14 | E5: =IF('Setup'!$B$5="","",'Setup'!$B$5+D5) | F5: =IF(OR(E5="",G5="Done"),"",E5-TODAY()) | J5: launch-countdown.today.2 | K5: =IF(OR(G5="Done",G5="Skipped"),"",E5)
A6: 3 | B6: Today | C6: Copy this countdown into Google Sheets, Notion or your notes app. | D6: -14 | E6: =IF('Setup'!$B$5="","",'Setup'!$B$5+D6) | F6: =IF(OR(E6="",G6="Done"),"",E6-TODAY()) | J6: launch-countdown.today.3 | K6: =IF(OR(G6="Done",G6="Skipped"),"",E6)
A7: 4 | B7: Two weeks before: set up the foundation | C7: Finish your One-Page Offer. | D7: -8 | E7: =IF('Setup'!$B$5="","",'Setup'!$B$5+D7) | F7: =IF(OR(E7="",G7="Done"),"",E7-TODAY()) | J7: launch-countdown.t14.1 | K7: =IF(OR(G7="Done",G7="Skipped"),"",E7)
A8: 5 | B8: Two weeks before: set up the foundation | C8: Fill in your Landing Page Brief and build the page. | D8: -8 | E8: =IF('Setup'!$B$5="","",'Setup'!$B$5+D8) | F8: =IF(OR(E8="",G8="Done"),"",E8-TODAY()) | J8: launch-countdown.t14.2 | K8: =IF(OR(G8="Done",G8="Skipped"),"",E8)
A9: 6 | B9: Two weeks before: set up the foundation | C9: Run the five-point pre-launch check on your phone. | D9: -8 | E9: =IF('Setup'!$B$5="","",'Setup'!$B$5+D9) | F9: =IF(OR(E9="",G9="Done"),"",E9-TODAY()) | J9: launch-countdown.t14.3 | K9: =IF(OR(G9="Done",G9="Skipped"),"",E9)
A10: 7 | B10: Two weeks before: set up the foundation | C10: Set up payments: Shopify Payments for a store, or a payment link for a service. | D10: -8 | E10: =IF('Setup'!$B$5="","",'Setup'!$B$5+D10) | F10: =IF(OR(E10="",G10="Done"),"",E10-TODAY()) | J10: launch-countdown.t14.4 | K10: =IF(OR(G10="Done",G10="Skipped"),"",E10)
A11: 8 | B11: Two weeks before: set up the foundation | C11: Make a real payment with your own card, then refund it. | D11: -8 | E11: =IF('Setup'!$B$5="","",'Setup'!$B$5+D11) | F11: =IF(OR(E11="",G11="Done"),"",E11-TODAY()) | J11: launch-countdown.t14.5 | K11: =IF(OR(G11="Done",G11="Skipped"),"",E11)
A12: 9 | B12: Two weeks before: set up the foundation | C12: Look into registering your business. Check your local rules or ask a professional. This isn't legal or tax advice. | D12: -8 | E12: =IF('Setup'!$B$5="","",'Setup'!$B$5+D12) | F12: =IF(OR(E12="",G12="Done"),"",E12-TODAY()) | J12: launch-countdown.t14.6 | K12: =IF(OR(G12="Done",G12="Skipped"),"",E12)
A13: 10 | B13: Two weeks before: set up the foundation | C13: Set up a separate way to track business money. See Before You Take Money. | D13: -8 | E13: =IF('Setup'!$B$5="","",'Setup'!$B$5+D13) | F13: =IF(OR(E13="",G13="Done"),"",E13-TODAY()) | J13: launch-countdown.t14.7 | K13: =IF(OR(G13="Done",G13="Skipped"),"",E13)
A14: 11 | B14: Two weeks before: set up the foundation | C14: Write your delivery steps: everything that happens after someone pays. | D14: -8 | E14: =IF('Setup'!$B$5="","",'Setup'!$B$5+D14) | F14: =IF(OR(E14="",G14="Done"),"",E14-TODAY()) | J14: launch-countdown.t14.8 | K14: =IF(OR(G14="Done",G14="Skipped"),"",E14)
A15: 12 | B15: Two weeks before: set up the foundation | C15: Do one full test delivery with a friend. | D15: -8 | E15: =IF('Setup'!$B$5="","",'Setup'!$B$5+D15) | F15: =IF(OR(E15="",G15="Done"),"",E15-TODAY()) | J15: launch-countdown.t14.9 | K15: =IF(OR(G15="Done",G15="Skipped"),"",E15)
... A45: 42 | B45: The week after: ask, learn, decide | C45: Set up simple revenue and expense tracking, and ask a professional about taxes where you live. | D45: 13 | E45: =IF('Setup'!$B$5="","",'Setup'!$B$5+D45) | F45: =IF(OR(E45="",G45="Done"),"",E45-TODAY()) | J45: launch-countdown.after.8 | K45: =IF(OR(G45="Done",G45="Skipped"),"",E45)
