Workbook

Sheet Start here
B2: 127 · BUILD TRACK · BUILDER
B3: Business Budget
B4: Plan what comes in and goes out each month, type the real numbers as the year goes, and see where you are over or under.
B6: HOW TO USE IT
B7: 1. Budget tab: one line per income or cost. Pick Income or Cost and a category.
B8: 2. Type the planned amount per month for each line.
B9: 3. At the end of each month, type the real amount in that month's column.
B10: 4. Read the grey columns: total so far, plan so far, and the gap. Green is good, red needs a look.
B11: 5. Summary tab: planned profit per month and real profit so far.
B13: CELL COLORS
B14: White cells: you type here.
B15: Grey cells: calculated for you. Leave them alone.
... B26: Template drafted from Eli Christiansen's frameworks. © 127 Group LLC. For your own business use.

Sheet Budget
A1: Business budget
A2: Plan each line once. Type the real amount at the end of each month.
A3: Line | B3: Income or cost | C3: Category | D3: Plan per month ($) | E3: Jan | F3: Feb | G3: Mar | H3: Apr | I3: May | J3: Jun | K3: Jul | L3: Aug | M3: Sep | N3: Oct | O3: Nov | P3: Dec | Q3: Real so far ($) | R3: Plan so far ($) | S3: Gap ($, + is good)
Q4: =IF(COUNT(E4:P4)=0,"",SUM(E4:P4)) | R4: =IF(OR(D4="",COUNT(E4:P4)=0),"",D4*COUNT(E4:P4)) | S4: =IF(OR(Q4="",R4=""),"",IF(B4="Income",Q4-R4,R4-Q4))
Q5: =IF(COUNT(E5:P5)=0,"",SUM(E5:P5)) | R5: =IF(OR(D5="",COUNT(E5:P5)=0),"",D5*COUNT(E5:P5)) | S5: =IF(OR(Q5="",R5=""),"",IF(B5="Income",Q5-R5,R5-Q5))
Q6: =IF(COUNT(E6:P6)=0,"",SUM(E6:P6)) | R6: =IF(OR(D6="",COUNT(E6:P6)=0),"",D6*COUNT(E6:P6)) | S6: =IF(OR(Q6="",R6=""),"",IF(B6="Income",Q6-R6,R6-Q6))
Q7: =IF(COUNT(E7:P7)=0,"",SUM(E7:P7)) | R7: =IF(OR(D7="",COUNT(E7:P7)=0),"",D7*COUNT(E7:P7)) | S7: =IF(OR(Q7="",R7=""),"",IF(B7="Income",Q7-R7,R7-Q7))
Q8: =IF(COUNT(E8:P8)=0,"",SUM(E8:P8)) | R8: =IF(OR(D8="",COUNT(E8:P8)=0),"",D8*COUNT(E8:P8)) | S8: =IF(OR(Q8="",R8=""),"",IF(B8="Income",Q8-R8,R8-Q8))
Q9: =IF(COUNT(E9:P9)=0,"",SUM(E9:P9)) | R9: =IF(OR(D9="",COUNT(E9:P9)=0),"",D9*COUNT(E9:P9)) | S9: =IF(OR(Q9="",R9=""),"",IF(B9="Income",Q9-R9,R9-Q9))
Q10: =IF(COUNT(E10:P10)=0,"",SUM(E10:P10)) | R10: =IF(OR(D10="",COUNT(E10:P10)=0),"",D10*COUNT(E10:P10)) | S10: =IF(OR(Q10="",R10=""),"",IF(B10="Income",Q10-R10,R10-Q10))
Q11: =IF(COUNT(E11:P11)=0,"",SUM(E11:P11)) | R11: =IF(OR(D11="",COUNT(E11:P11)=0),"",D11*COUNT(E11:P11)) | S11: =IF(OR(Q11="",R11=""),"",IF(B11="Income",Q11-R11,R11-Q11))
Q12: =IF(COUNT(E12:P12)=0,"",SUM(E12:P12)) | R12: =IF(OR(D12="",COUNT(E12:P12)=0),"",D12*COUNT(E12:P12)) | S12: =IF(OR(Q12="",R12=""),"",IF(B12="Income",Q12-R12,R12-Q12))
Q13: =IF(COUNT(E13:P13)=0,"",SUM(E13:P13)) | R13: =IF(OR(D13="",COUNT(E13:P13)=0),"",D13*COUNT(E13:P13)) | S13: =IF(OR(Q13="",R13=""),"",IF(B13="Income",Q13-R13,R13-Q13))
Q14: =IF(COUNT(E14:P14)=0,"",SUM(E14:P14)) | R14: =IF(OR(D14="",COUNT(E14:P14)=0),"",D14*COUNT(E14:P14)) | S14: =IF(OR(Q14="",R14=""),"",IF(B14="Income",Q14-R14,R14-Q14))
Q15: =IF(COUNT(E15:P15)=0,"",SUM(E15:P15)) | R15: =IF(OR(D15="",COUNT(E15:P15)=0),"",D15*COUNT(E15:P15)) | S15: =IF(OR(Q15="",R15=""),"",IF(B15="Income",Q15-R15,R15-Q15))
... Q43: =IF(COUNT(E43:P43)=0,"",SUM(E43:P43)) | R43: =IF(OR(D43="",COUNT(E43:P43)=0),"",D43*COUNT(E43:P43)) | S43: =IF(OR(Q43="",R43=""),"",IF(B43="Income",Q43-R43,R43-Q43))

Sheet Summary
A1: Budget summary
A2: Calculated from the Budget tab.
A4: PLAN PER MONTH
A5: Planned income ($) | B5: =SUMIF('Budget'!$B$4:$B$43,"Income",'Budget'!$D$4:$D$43)
A6: Planned costs ($) | B6: =SUMIF('Budget'!$B$4:$B$43,"Cost",'Budget'!$D$4:$D$43)
A7: Planned profit per month ($) | B7: =$B$5-$B$6
A9: REAL SO FAR
A10: Real income so far ($) | B10: =SUMIF('Budget'!$B$4:$B$43,"Income",'Budget'!$Q$4:$Q$43)
A11: Real costs so far ($) | B11: =SUMIF('Budget'!$B$4:$B$43,"Cost",'Budget'!$Q$4:$Q$43)
A12: Real profit so far ($) | B12: =$B$10-$B$11
A13: Lines over plan | B13: =COUNTIF('Budget'!$S$4:$S$43,"<0")
A14: Read | B14: =IF($B$5=0,"Add your income and cost lines on the Budget tab.",IF($B$10=0,"Type real numbers at the end of the month to compare.",IF($B$13=0,"Every line is on or better than plan so far.",$B$13&" lines are worse than plan. Look at the red gaps on the Budget tab first.")))
