Workbook

Sheet Start here
B2: 127 · GROW TRACK · BUILDER
B3: Weekly Founder Scorecard
B4: Ten minutes every Monday: your five numbers, the conversion rate between each step, week-over-week change and one decision for next week.
B6: HOW TO USE IT
B7: 1. Each Monday, pull last week's numbers from the same places: platform analytics, site dashboard, DMs, payment app.
B8: 2. Type them into the next row of the Scorecard tab. Zero is a number. Enter it.
B9: 3. Add your inputs too: posts, messages sent, hours. When everything drops, check these first.
B10: 4. Read the grey columns: each conversion rate, the change from last week and the biggest drop.
B11: 5. Write one double down, one pause, one kill and the one test for next week.
B12: 6. Open This week for the summary and the Charts tab for the trend. One week is a data point. Three is a trend.
B13: 7. Want it emailed to you every Monday? Set up the Monday Scorecard Email recipe on this sheet.
B15: CELL COLORS
... B28: Template drafted from Eli Christiansen's frameworks. © 127 Group LLC. For your own business use.

Sheet Scorecard
A1: Weekly Founder Scorecard
A2: Same day, same sources, every week. Grey columns do the math.
A3: Week | B3: Week of (Monday) | C3: Reach (views, impressions) | D3: Visits (profile or site) | E3: Leads (DMs, forms, calls) | F3: Sales (orders, customers) | G3: Revenue ($) | H3: Posts published | I3: Messages sent | J3: Hours on the business | K3: Reach to visits | L3: Visits to leads | M3: Leads to sales | N3: Revenue per sale | O3: Reach vs last week | P3: Leads vs last week | Q3: Sales vs last week | R3: Revenue vs last week | S3: Biggest drop in a rate | T3: Double down on | U3: Pause | V3: Kill | W3: One test next week | X3: Where the numbers came from | Y3: h1 | Z3: h2 | AA3: h3
A4: 1 | K4: =IF(OR(D4="",N(C4)=0),"",D4/C4) | L4: =IF(OR(E4="",N(D4)=0),"",E4/D4) | M4: =IF(OR(F4="",N(E4)=0),"",F4/E4) | N4: =IF(OR(G4="",N(F4)=0),"",G4/F4) | O4: =IF(OR(1=1,C4="",N(C3)=0),"",C4/C3-1) | P4: =IF(OR(1=1,E4="",N(E3)=0),"",E4/E3-1) | Q4: =IF(OR(1=1,F4="",N(F3)=0),"",F4/F3-1) | R4: =IF(OR(1=1,G4="",N(G3)=0),"",G4/G3-1) | S4: =IF(C4="","",IF(1=1,"Week 1: your baseline",IF(AND(ISNUMBER(O4),ISNUMBER(P4),ISNUMBER(Q4),N(O4)<0,N(P4)<0,N(Q4)<0),"Everything down: check posts and messages sent first",IF(COUNT(Y4:AA4)=0,"",IF(MIN(Y4:AA4)>=0,"No rate dropped. Do more of what worked.",CHOOSE(MATCH(MIN(Y4:AA4),Y4:AA4,0),"Reach to visits: fix bio, pinned posts, first line","Visits to leads: make the offer and next step clearer","Leads to sales: reread your DMs and price framing")))))) | Y4: =IF(OR(1=1,NOT(ISNUMBER(K4)),NOT(ISNUMBER(K3))),"",IF(K3=0,"",K4/K3-1)) | Z4: =IF(OR(1=1,NOT(ISNUMBER(L4)),NOT(ISNUMBER(L3))),"",IF(L3=0,"",L4/L3-1)) | AA4: =IF(OR(1=1,NOT(ISNUMBER(M4)),NOT(ISNUMBER(M3))),"",IF(M3=0,"",M4/M3-1))
A5: 2 | B5: =IF(B4="","",B4+7) | K5: =IF(OR(D5="",N(C5)=0),"",D5/C5) | L5: =IF(OR(E5="",N(D5)=0),"",E5/D5) | M5: =IF(OR(F5="",N(E5)=0),"",F5/E5) | N5: =IF(OR(G5="",N(F5)=0),"",G5/F5) | O5: =IF(OR(2=1,C5="",N(C4)=0),"",C5/C4-1) | P5: =IF(OR(2=1,E5="",N(E4)=0),"",E5/E4-1) | Q5: =IF(OR(2=1,F5="",N(F4)=0),"",F5/F4-1) | R5: =IF(OR(2=1,G5="",N(G4)=0),"",G5/G4-1) | S5: =IF(C5="","",IF(2=1,"Week 1: your baseline",IF(AND(ISNUMBER(O5),ISNUMBER(P5),ISNUMBER(Q5),N(O5)<0,N(P5)<0,N(Q5)<0),"Everything down: check posts and messages sent first",IF(COUNT(Y5:AA5)=0,"",IF(MIN(Y5:AA5)>=0,"No rate dropped. Do more of what worked.",CHOOSE(MATCH(MIN(Y5:AA5),Y5:AA5,0),"Reach to visits: fix bio, pinned posts, first line","Visits to leads: make the offer and next step clearer","Leads to sales: reread your DMs and price framing")))))) | Y5: =IF(OR(2=1,NOT(ISNUMBER(K5)),NOT(ISNUMBER(K4))),"",IF(K4=0,"",K5/K4-1)) | Z5: =IF(OR(2=1,NOT(ISNUMBER(L5)),NOT(ISNUMBER(L4))),"",IF(L4=0,"",L5/L4-1)) | AA5: =IF(OR(2=1,NOT(ISNUMBER(M5)),NOT(ISNUMBER(M4))),"",IF(M4=0,"",M5/M4-1))
A6: 3 | B6: =IF(B5="","",B5+7) | K6: =IF(OR(D6="",N(C6)=0),"",D6/C6) | L6: =IF(OR(E6="",N(D6)=0),"",E6/D6) | M6: =IF(OR(F6="",N(E6)=0),"",F6/E6) | N6: =IF(OR(G6="",N(F6)=0),"",G6/F6) | O6: =IF(OR(3=1,C6="",N(C5)=0),"",C6/C5-1) | P6: =IF(OR(3=1,E6="",N(E5)=0),"",E6/E5-1) | Q6: =IF(OR(3=1,F6="",N(F5)=0),"",F6/F5-1) | R6: =IF(OR(3=1,G6="",N(G5)=0),"",G6/G5-1) | S6: =IF(C6="","",IF(3=1,"Week 1: your baseline",IF(AND(ISNUMBER(O6),ISNUMBER(P6),ISNUMBER(Q6),N(O6)<0,N(P6)<0,N(Q6)<0),"Everything down: check posts and messages sent first",IF(COUNT(Y6:AA6)=0,"",IF(MIN(Y6:AA6)>=0,"No rate dropped. Do more of what worked.",CHOOSE(MATCH(MIN(Y6:AA6),Y6:AA6,0),"Reach to visits: fix bio, pinned posts, first line","Visits to leads: make the offer and next step clearer","Leads to sales: reread your DMs and price framing")))))) | Y6: =IF(OR(3=1,NOT(ISNUMBER(K6)),NOT(ISNUMBER(K5))),"",IF(K5=0,"",K6/K5-1)) | Z6: =IF(OR(3=1,NOT(ISNUMBER(L6)),NOT(ISNUMBER(L5))),"",IF(L5=0,"",L6/L5-1)) | AA6: =IF(OR(3=1,NOT(ISNUMBER(M6)),NOT(ISNUMBER(M5))),"",IF(M5=0,"",M6/M5-1))
A7: 4 | B7: =IF(B6="","",B6+7) | K7: =IF(OR(D7="",N(C7)=0),"",D7/C7) | L7: =IF(OR(E7="",N(D7)=0),"",E7/D7) | M7: =IF(OR(F7="",N(E7)=0),"",F7/E7) | N7: =IF(OR(G7="",N(F7)=0),"",G7/F7) | O7: =IF(OR(4=1,C7="",N(C6)=0),"",C7/C6-1) | P7: =IF(OR(4=1,E7="",N(E6)=0),"",E7/E6-1) | Q7: =IF(OR(4=1,F7="",N(F6)=0),"",F7/F6-1) | R7: =IF(OR(4=1,G7="",N(G6)=0),"",G7/G6-1) | S7: =IF(C7="","",IF(4=1,"Week 1: your baseline",IF(AND(ISNUMBER(O7),ISNUMBER(P7),ISNUMBER(Q7),N(O7)<0,N(P7)<0,N(Q7)<0),"Everything down: check posts and messages sent first",IF(COUNT(Y7:AA7)=0,"",IF(MIN(Y7:AA7)>=0,"No rate dropped. Do more of what worked.",CHOOSE(MATCH(MIN(Y7:AA7),Y7:AA7,0),"Reach to visits: fix bio, pinned posts, first line","Visits to leads: make the offer and next step clearer","Leads to sales: reread your DMs and price framing")))))) | Y7: =IF(OR(4=1,NOT(ISNUMBER(K7)),NOT(ISNUMBER(K6))),"",IF(K6=0,"",K7/K6-1)) | Z7: =IF(OR(4=1,NOT(ISNUMBER(L7)),NOT(ISNUMBER(L6))),"",IF(L6=0,"",L7/L6-1)) | AA7: =IF(OR(4=1,NOT(ISNUMBER(M7)),NOT(ISNUMBER(M6))),"",IF(M6=0,"",M7/M6-1))
A8: 5 | B8: =IF(B7="","",B7+7) | K8: =IF(OR(D8="",N(C8)=0),"",D8/C8) | L8: =IF(OR(E8="",N(D8)=0),"",E8/D8) | M8: =IF(OR(F8="",N(E8)=0),"",F8/E8) | N8: =IF(OR(G8="",N(F8)=0),"",G8/F8) | O8: =IF(OR(5=1,C8="",N(C7)=0),"",C8/C7-1) | P8: =IF(OR(5=1,E8="",N(E7)=0),"",E8/E7-1) | Q8: =IF(OR(5=1,F8="",N(F7)=0),"",F8/F7-1) | R8: =IF(OR(5=1,G8="",N(G7)=0),"",G8/G7-1) | S8: =IF(C8="","",IF(5=1,"Week 1: your baseline",IF(AND(ISNUMBER(O8),ISNUMBER(P8),ISNUMBER(Q8),N(O8)<0,N(P8)<0,N(Q8)<0),"Everything down: check posts and messages sent first",IF(COUNT(Y8:AA8)=0,"",IF(MIN(Y8:AA8)>=0,"No rate dropped. Do more of what worked.",CHOOSE(MATCH(MIN(Y8:AA8),Y8:AA8,0),"Reach to visits: fix bio, pinned posts, first line","Visits to leads: make the offer and next step clearer","Leads to sales: reread your DMs and price framing")))))) | Y8: =IF(OR(5=1,NOT(ISNUMBER(K8)),NOT(ISNUMBER(K7))),"",IF(K7=0,"",K8/K7-1)) | Z8: =IF(OR(5=1,NOT(ISNUMBER(L8)),NOT(ISNUMBER(L7))),"",IF(L7=0,"",L8/L7-1)) | AA8: =IF(OR(5=1,NOT(ISNUMBER(M8)),NOT(ISNUMBER(M7))),"",IF(M7=0,"",M8/M7-1))
A9: 6 | B9: =IF(B8="","",B8+7) | K9: =IF(OR(D9="",N(C9)=0),"",D9/C9) | L9: =IF(OR(E9="",N(D9)=0),"",E9/D9) | M9: =IF(OR(F9="",N(E9)=0),"",F9/E9) | N9: =IF(OR(G9="",N(F9)=0),"",G9/F9) | O9: =IF(OR(6=1,C9="",N(C8)=0),"",C9/C8-1) | P9: =IF(OR(6=1,E9="",N(E8)=0),"",E9/E8-1) | Q9: =IF(OR(6=1,F9="",N(F8)=0),"",F9/F8-1) | R9: =IF(OR(6=1,G9="",N(G8)=0),"",G9/G8-1) | S9: =IF(C9="","",IF(6=1,"Week 1: your baseline",IF(AND(ISNUMBER(O9),ISNUMBER(P9),ISNUMBER(Q9),N(O9)<0,N(P9)<0,N(Q9)<0),"Everything down: check posts and messages sent first",IF(COUNT(Y9:AA9)=0,"",IF(MIN(Y9:AA9)>=0,"No rate dropped. Do more of what worked.",CHOOSE(MATCH(MIN(Y9:AA9),Y9:AA9,0),"Reach to visits: fix bio, pinned posts, first line","Visits to leads: make the offer and next step clearer","Leads to sales: reread your DMs and price framing")))))) | Y9: =IF(OR(6=1,NOT(ISNUMBER(K9)),NOT(ISNUMBER(K8))),"",IF(K8=0,"",K9/K8-1)) | Z9: =IF(OR(6=1,NOT(ISNUMBER(L9)),NOT(ISNUMBER(L8))),"",IF(L8=0,"",L9/L8-1)) | AA9: =IF(OR(6=1,NOT(ISNUMBER(M9)),NOT(ISNUMBER(M8))),"",IF(M8=0,"",M9/M8-1))
A10: 7 | B10: =IF(B9="","",B9+7) | K10: =IF(OR(D10="",N(C10)=0),"",D10/C10) | L10: =IF(OR(E10="",N(D10)=0),"",E10/D10) | M10: =IF(OR(F10="",N(E10)=0),"",F10/E10) | N10: =IF(OR(G10="",N(F10)=0),"",G10/F10) | O10: =IF(OR(7=1,C10="",N(C9)=0),"",C10/C9-1) | P10: =IF(OR(7=1,E10="",N(E9)=0),"",E10/E9-1) | Q10: =IF(OR(7=1,F10="",N(F9)=0),"",F10/F9-1) | R10: =IF(OR(7=1,G10="",N(G9)=0),"",G10/G9-1) | S10: =IF(C10="","",IF(7=1,"Week 1: your baseline",IF(AND(ISNUMBER(O10),ISNUMBER(P10),ISNUMBER(Q10),N(O10)<0,N(P10)<0,N(Q10)<0),"Everything down: check posts and messages sent first",IF(COUNT(Y10:AA10)=0,"",IF(MIN(Y10:AA10)>=0,"No rate dropped. Do more of what worked.",CHOOSE(MATCH(MIN(Y10:AA10),Y10:AA10,0),"Reach to visits: fix bio, pinned posts, first line","Visits to leads: make the offer and next step clearer","Leads to sales: reread your DMs and price framing")))))) | Y10: =IF(OR(7=1,NOT(ISNUMBER(K10)),NOT(ISNUMBER(K9))),"",IF(K9=0,"",K10/K9-1)) | Z10: =IF(OR(7=1,NOT(ISNUMBER(L10)),NOT(ISNUMBER(L9))),"",IF(L9=0,"",L10/L9-1)) | AA10: =IF(OR(7=1,NOT(ISNUMBER(M10)),NOT(ISNUMBER(M9))),"",IF(M9=0,"",M10/M9-1))
A11: 8 | B11: =IF(B10="","",B10+7) | K11: =IF(OR(D11="",N(C11)=0),"",D11/C11) | L11: =IF(OR(E11="",N(D11)=0),"",E11/D11) | M11: =IF(OR(F11="",N(E11)=0),"",F11/E11) | N11: =IF(OR(G11="",N(F11)=0),"",G11/F11) | O11: =IF(OR(8=1,C11="",N(C10)=0),"",C11/C10-1) | P11: =IF(OR(8=1,E11="",N(E10)=0),"",E11/E10-1) | Q11: =IF(OR(8=1,F11="",N(F10)=0),"",F11/F10-1) | R11: =IF(OR(8=1,G11="",N(G10)=0),"",G11/G10-1) | S11: =IF(C11="","",IF(8=1,"Week 1: your baseline",IF(AND(ISNUMBER(O11),ISNUMBER(P11),ISNUMBER(Q11),N(O11)<0,N(P11)<0,N(Q11)<0),"Everything down: check posts and messages sent first",IF(COUNT(Y11:AA11)=0,"",IF(MIN(Y11:AA11)>=0,"No rate dropped. Do more of what worked.",CHOOSE(MATCH(MIN(Y11:AA11),Y11:AA11,0),"Reach to visits: fix bio, pinned posts, first line","Visits to leads: make the offer and next step clearer","Leads to sales: reread your DMs and price framing")))))) | Y11: =IF(OR(8=1,NOT(ISNUMBER(K11)),NOT(ISNUMBER(K10))),"",IF(K10=0,"",K11/K10-1)) | Z11: =IF(OR(8=1,NOT(ISNUMBER(L11)),NOT(ISNUMBER(L10))),"",IF(L10=0,"",L11/L10-1)) | AA11: =IF(OR(8=1,NOT(ISNUMBER(M11)),NOT(ISNUMBER(M10))),"",IF(M10=0,"",M11/M10-1))
A12: 9 | B12: =IF(B11="","",B11+7) | K12: =IF(OR(D12="",N(C12)=0),"",D12/C12) | L12: =IF(OR(E12="",N(D12)=0),"",E12/D12) | M12: =IF(OR(F12="",N(E12)=0),"",F12/E12) | N12: =IF(OR(G12="",N(F12)=0),"",G12/F12) | O12: =IF(OR(9=1,C12="",N(C11)=0),"",C12/C11-1) | P12: =IF(OR(9=1,E12="",N(E11)=0),"",E12/E11-1) | Q12: =IF(OR(9=1,F12="",N(F11)=0),"",F12/F11-1) | R12: =IF(OR(9=1,G12="",N(G11)=0),"",G12/G11-1) | S12: =IF(C12="","",IF(9=1,"Week 1: your baseline",IF(AND(ISNUMBER(O12),ISNUMBER(P12),ISNUMBER(Q12),N(O12)<0,N(P12)<0,N(Q12)<0),"Everything down: check posts and messages sent first",IF(COUNT(Y12:AA12)=0,"",IF(MIN(Y12:AA12)>=0,"No rate dropped. Do more of what worked.",CHOOSE(MATCH(MIN(Y12:AA12),Y12:AA12,0),"Reach to visits: fix bio, pinned posts, first line","Visits to leads: make the offer and next step clearer","Leads to sales: reread your DMs and price framing")))))) | Y12: =IF(OR(9=1,NOT(ISNUMBER(K12)),NOT(ISNUMBER(K11))),"",IF(K11=0,"",K12/K11-1)) | Z12: =IF(OR(9=1,NOT(ISNUMBER(L12)),NOT(ISNUMBER(L11))),"",IF(L11=0,"",L12/L11-1)) | AA12: =IF(OR(9=1,NOT(ISNUMBER(M12)),NOT(ISNUMBER(M11))),"",IF(M11=0,"",M12/M11-1))
A13: 10 | B13: =IF(B12="","",B12+7) | K13: =IF(OR(D13="",N(C13)=0),"",D13/C13) | L13: =IF(OR(E13="",N(D13)=0),"",E13/D13) | M13: =IF(OR(F13="",N(E13)=0),"",F13/E13) | N13: =IF(OR(G13="",N(F13)=0),"",G13/F13) | O13: =IF(OR(10=1,C13="",N(C12)=0),"",C13/C12-1) | P13: =IF(OR(10=1,E13="",N(E12)=0),"",E13/E12-1) | Q13: =IF(OR(10=1,F13="",N(F12)=0),"",F13/F12-1) | R13: =IF(OR(10=1,G13="",N(G12)=0),"",G13/G12-1) | S13: =IF(C13="","",IF(10=1,"Week 1: your baseline",IF(AND(ISNUMBER(O13),ISNUMBER(P13),ISNUMBER(Q13),N(O13)<0,N(P13)<0,N(Q13)<0),"Everything down: check posts and messages sent first",IF(COUNT(Y13:AA13)=0,"",IF(MIN(Y13:AA13)>=0,"No rate dropped. Do more of what worked.",CHOOSE(MATCH(MIN(Y13:AA13),Y13:AA13,0),"Reach to visits: fix bio, pinned posts, first line","Visits to leads: make the offer and next step clearer","Leads to sales: reread your DMs and price framing")))))) | Y13: =IF(OR(10=1,NOT(ISNUMBER(K13)),NOT(ISNUMBER(K12))),"",IF(K12=0,"",K13/K12-1)) | Z13: =IF(OR(10=1,NOT(ISNUMBER(L13)),NOT(ISNUMBER(L12))),"",IF(L12=0,"",L13/L12-1)) | AA13: =IF(OR(10=1,NOT(ISNUMBER(M13)),NOT(ISNUMBER(M12))),"",IF(M12=0,"",M13/M12-1))
A14: 11 | B14: =IF(B13="","",B13+7) | K14: =IF(OR(D14="",N(C14)=0),"",D14/C14) | L14: =IF(OR(E14="",N(D14)=0),"",E14/D14) | M14: =IF(OR(F14="",N(E14)=0),"",F14/E14) | N14: =IF(OR(G14="",N(F14)=0),"",G14/F14) | O14: =IF(OR(11=1,C14="",N(C13)=0),"",C14/C13-1) | P14: =IF(OR(11=1,E14="",N(E13)=0),"",E14/E13-1) | Q14: =IF(OR(11=1,F14="",N(F13)=0),"",F14/F13-1) | R14: =IF(OR(11=1,G14="",N(G13)=0),"",G14/G13-1) | S14: =IF(C14="","",IF(11=1,"Week 1: your baseline",IF(AND(ISNUMBER(O14),ISNUMBER(P14),ISNUMBER(Q14),N(O14)<0,N(P14)<0,N(Q14)<0),"Everything down: check posts and messages sent first",IF(COUNT(Y14:AA14)=0,"",IF(MIN(Y14:AA14)>=0,"No rate dropped. Do more of what worked.",CHOOSE(MATCH(MIN(Y14:AA14),Y14:AA14,0),"Reach to visits: fix bio, pinned posts, first line","Visits to leads: make the offer and next step clearer","Leads to sales: reread your DMs and price framing")))))) | Y14: =IF(OR(11=1,NOT(ISNUMBER(K14)),NOT(ISNUMBER(K13))),"",IF(K13=0,"",K14/K13-1)) | Z14: =IF(OR(11=1,NOT(ISNUMBER(L14)),NOT(ISNUMBER(L13))),"",IF(L13=0,"",L14/L13-1)) | AA14: =IF(OR(11=1,NOT(ISNUMBER(M14)),NOT(ISNUMBER(M13))),"",IF(M13=0,"",M14/M13-1))
A15: 12 | B15: =IF(B14="","",B14+7) | K15: =IF(OR(D15="",N(C15)=0),"",D15/C15) | L15: =IF(OR(E15="",N(D15)=0),"",E15/D15) | M15: =IF(OR(F15="",N(E15)=0),"",F15/E15) | N15: =IF(OR(G15="",N(F15)=0),"",G15/F15) | O15: =IF(OR(12=1,C15="",N(C14)=0),"",C15/C14-1) | P15: =IF(OR(12=1,E15="",N(E14)=0),"",E15/E14-1) | Q15: =IF(OR(12=1,F15="",N(F14)=0),"",F15/F14-1) | R15: =IF(OR(12=1,G15="",N(G14)=0),"",G15/G14-1) | S15: =IF(C15="","",IF(12=1,"Week 1: your baseline",IF(AND(ISNUMBER(O15),ISNUMBER(P15),ISNUMBER(Q15),N(O15)<0,N(P15)<0,N(Q15)<0),"Everything down: check posts and messages sent first",IF(COUNT(Y15:AA15)=0,"",IF(MIN(Y15:AA15)>=0,"No rate dropped. Do more of what worked.",CHOOSE(MATCH(MIN(Y15:AA15),Y15:AA15,0),"Reach to visits: fix bio, pinned posts, first line","Visits to leads: make the offer and next step clearer","Leads to sales: reread your DMs and price framing")))))) | Y15: =IF(OR(12=1,NOT(ISNUMBER(K15)),NOT(ISNUMBER(K14))),"",IF(K14=0,"",K15/K14-1)) | Z15: =IF(OR(12=1,NOT(ISNUMBER(L15)),NOT(ISNUMBER(L14))),"",IF(L14=0,"",L15/L14-1)) | AA15: =IF(OR(12=1,NOT(ISNUMBER(M15)),NOT(ISNUMBER(M14))),"",IF(M14=0,"",M15/M14-1))
A16: 13 | B16: =IF(B15="","",B15+7) | K16: =IF(OR(D16="",N(C16)=0),"",D16/C16) | L16: =IF(OR(E16="",N(D16)=0),"",E16/D16) | M16: =IF(OR(F16="",N(E16)=0),"",F16/E16) | N16: =IF(OR(G16="",N(F16)=0),"",G16/F16) | O16: =IF(OR(13=1,C16="",N(C15)=0),"",C16/C15-1) | P16: =IF(OR(13=1,E16="",N(E15)=0),"",E16/E15-1) | Q16: =IF(OR(13=1,F16="",N(F15)=0),"",F16/F15-1) | R16: =IF(OR(13=1,G16="",N(G15)=0),"",G16/G15-1) | S16: =IF(C16="","",IF(13=1,"Week 1: your baseline",IF(AND(ISNUMBER(O16),ISNUMBER(P16),ISNUMBER(Q16),N(O16)<0,N(P16)<0,N(Q16)<0),"Everything down: check posts and messages sent first",IF(COUNT(Y16:AA16)=0,"",IF(MIN(Y16:AA16)>=0,"No rate dropped. Do more of what worked.",CHOOSE(MATCH(MIN(Y16:AA16),Y16:AA16,0),"Reach to visits: fix bio, pinned posts, first line","Visits to leads: make the offer and next step clearer","Leads to sales: reread your DMs and price framing")))))) | Y16: =IF(OR(13=1,NOT(ISNUMBER(K16)),NOT(ISNUMBER(K15))),"",IF(K15=0,"",K16/K15-1)) | Z16: =IF(OR(13=1,NOT(ISNUMBER(L16)),NOT(ISNUMBER(L15))),"",IF(L15=0,"",L16/L15-1)) | AA16: =IF(OR(13=1,NOT(ISNUMBER(M16)),NOT(ISNUMBER(M15))),"",IF(M15=0,"",M16/M15-1))

Sheet This week
A1: This week at a glance
A2: Shows your latest week with numbers, and how far you have come since week 1.
A4: LATEST WEEK | B4: Latest | C4: Week 1 | D4: Change
A5: Week number | B5: =IF(COUNT('Scorecard'!$C$4:$C$16)=0,"",INDEX('Scorecard'!$A$4:$A$16,MATCH(9.99E+307,'Scorecard'!$C$4:$C$16))) | C5: =IF(COUNT('Scorecard'!$C$4:$C$16)=0,"",1) | D5: =""
A6: Reach | B6: =IF(COUNT('Scorecard'!$C$4:$C$16)=0,"",INDEX('Scorecard'!$C$4:$C$16,MATCH(9.99E+307,'Scorecard'!$C$4:$C$16))) | C6: =IF(COUNT('Scorecard'!$C$4:$C$16)=0,"",INDEX('Scorecard'!$C$4:$C$16,1)) | D6: =IF(OR(N($C$6)=0,$B$6=""),"",$B$6/$C$6-1)
A7: Visits | B7: =IF(COUNT('Scorecard'!$C$4:$C$16)=0,"",INDEX('Scorecard'!$D$4:$D$16,MATCH(9.99E+307,'Scorecard'!$C$4:$C$16))) | C7: =IF(COUNT('Scorecard'!$C$4:$C$16)=0,"",INDEX('Scorecard'!$D$4:$D$16,1)) | D7: =IF(OR(N($C$7)=0,$B$7=""),"",$B$7/$C$7-1)
A8: Leads | B8: =IF(COUNT('Scorecard'!$C$4:$C$16)=0,"",INDEX('Scorecard'!$E$4:$E$16,MATCH(9.99E+307,'Scorecard'!$C$4:$C$16))) | C8: =IF(COUNT('Scorecard'!$C$4:$C$16)=0,"",INDEX('Scorecard'!$E$4:$E$16,1)) | D8: =IF(OR(N($C$8)=0,$B$8=""),"",$B$8/$C$8-1)
A9: Sales | B9: =IF(COUNT('Scorecard'!$C$4:$C$16)=0,"",INDEX('Scorecard'!$F$4:$F$16,MATCH(9.99E+307,'Scorecard'!$C$4:$C$16))) | C9: =IF(COUNT('Scorecard'!$C$4:$C$16)=0,"",INDEX('Scorecard'!$F$4:$F$16,1)) | D9: =IF(OR(N($C$9)=0,$B$9=""),"",$B$9/$C$9-1)
A10: Revenue ($) | B10: =IF(COUNT('Scorecard'!$C$4:$C$16)=0,"",INDEX('Scorecard'!$G$4:$G$16,MATCH(9.99E+307,'Scorecard'!$C$4:$C$16))) | C10: =IF(COUNT('Scorecard'!$C$4:$C$16)=0,"",INDEX('Scorecard'!$G$4:$G$16,1)) | D10: =IF(OR(N($C$10)=0,$B$10=""),"",$B$10/$C$10-1)
A11: Reach to visits | B11: =IF(COUNT('Scorecard'!$C$4:$C$16)=0,"",INDEX('Scorecard'!$K$4:$K$16,MATCH(9.99E+307,'Scorecard'!$C$4:$C$16))) | C11: =IF(COUNT('Scorecard'!$C$4:$C$16)=0,"",INDEX('Scorecard'!$K$4:$K$16,1)) | D11: =""
A12: Visits to leads | B12: =IF(COUNT('Scorecard'!$C$4:$C$16)=0,"",INDEX('Scorecard'!$L$4:$L$16,MATCH(9.99E+307,'Scorecard'!$C$4:$C$16))) | C12: =IF(COUNT('Scorecard'!$C$4:$C$16)=0,"",INDEX('Scorecard'!$L$4:$L$16,1)) | D12: =""
A13: Leads to sales | B13: =IF(COUNT('Scorecard'!$C$4:$C$16)=0,"",INDEX('Scorecard'!$M$4:$M$16,MATCH(9.99E+307,'Scorecard'!$C$4:$C$16))) | C13: =IF(COUNT('Scorecard'!$C$4:$C$16)=0,"",INDEX('Scorecard'!$M$4:$M$16,1)) | D13: =""
A15: YOUR CALL THIS WEEK
A16: Biggest drop in a rate | B16: =IF(COUNT('Scorecard'!$C$4:$C$16)=0,"",INDEX('Scorecard'!$S$4:$S$16,MATCH(9.99E+307,'Scorecard'!$C$4:$C$16))&"")
A17: Double down on | B17: =IF(COUNT('Scorecard'!$C$4:$C$16)=0,"",INDEX('Scorecard'!$T$4:$T$16,MATCH(9.99E+307,'Scorecard'!$C$4:$C$16))&"")
A18: One test next week | B18: =IF(COUNT('Scorecard'!$C$4:$C$16)=0,"",INDEX('Scorecard'!$W$4:$W$16,MATCH(9.99E+307,'Scorecard'!$C$4:$C$16))&"")
A19: Total revenue logged ($) | B19: =SUM('Scorecard'!$G$4:$G$16)
A20: Weeks logged | B20: =COUNT('Scorecard'!$C$4:$C$16)

Sheet Charts
A1: Your trend
A2: Charts read from the Scorecard tab. Look for the step that moved most, up or down.
