Workbook

Sheet Start here
B2: 127 · GROW TRACK · BUILDER
B3: Ad Test Planner
B4: Plan a small, capped paid test, write your stop rule before you spend a dollar, then log each day so the sheet tells you when to stop.
B6: HOW TO USE IT
B7: 1. Answer the five readiness checks in Plan. Fewer than three yes? Skip paid for now and go back to outreach and content.
B8: 2. Enter the most you can lose without stress. That's your cap, for one test, not per month.
B9: 3. Enter a cautious guess for cost per click, your page's conversion rate and your price.
B10: 4. Read the expected visitors, sales and cost per sale. Write your stop rule before you launch the ad.
B11: 5. Each day of the test, log spend, clicks, visits and sales in Daily log.
B12: 6. When the sheet says stop, stop. Change one thing only, then run the next test with the same cap.
B14: CELL COLORS
B15: White cells: you type here.
... B29: Template drafted from Eli Christiansen's frameworks. © 127 Group LLC. For your own business use.

Sheet Plan
A1: Plan your test
A2: Decide what stop and go mean before you spend anything.
A4: READY FOR PAID? (ORGANIC BEFORE PAID)
A5: You have had at least 10 customer conversations
A6: Warm-list visitors bought or signed up on your page
A7: Your page answers your top three objections
A8: You know which post or message gets the best response
A9: You can lose the whole test budget without stress
A10: Readiness | B10: =IF(COUNTIF($B$5:$B$9,"Yes")>=4,"Ready to test",IF(COUNTIF($B$5:$B$9,"Yes")>=3,"Almost. Fix the no first if you can.","Skip paid for now. Outreach and content teach you more for free."))
A12: THE TEST
A13: Where you will run it
A14: Test cap: the most you can lose ($)
A15: Days the test runs
A16: Expected cost per click ($, a cautious guess)
A17: Landing page conversion rate (type 2% if 2 of every 100 visitors buy)
A18: Price of one sale ($)
A19: Profit from one sale after costs ($)
A21: WHAT TO EXPECT
A22: Daily budget ($) | B22: =IF(OR($B$14="",N($B$15)=0),"",$B$14/$B$15)
A23: Expected visitors | B23: =IF(OR($B$14="",N($B$16)=0),"",ROUND($B$14/$B$16,0))
A24: Expected sales | B24: =IF(OR($B$23="",$B$17=""),"",$B$23*$B$17)
A25: Expected cost per sale ($) | B25: =IF(OR($B$24="",N($B$24)=0),"",$B$14/$B$24)
A26: What one sale earns you ($) | B26: =IF($B$19<>"",$B$19,IF($B$18="","",$B$18))
A27: Worth running? | B27: =IF($B$25="","",IF($B$25<$B$26,"Expected cost per sale is under what a sale earns. Worth testing.","Each sale would cost more than it earns. Fix the page or offer first."))
A29: YOUR RULES (WRITE THEM BEFORE YOU LAUNCH)
A30: Stop rule (the two-sales rule) | B30: =IF($B$18="","","Pause if you spend "&TEXT(2*$B$18,"$#,##0")&" with zero sales, or hit your "&TEXT(N($B$14),"$#,##0")&" cap with cost per sale above what a sale earns.")
A31: What result would make you double down?
A32: If it fails, the one thing you will change first

Sheet Daily log
A1: Daily log
A2: Log once a day. The last column checks your stop rule for you.
A3: Date | B3: Spend ($) | C3: Impressions | D3: Clicks | E3: Page visits | F3: Sales | G3: Revenue ($) | H3: Cost per click | I3: Click rate | J3: Spend so far | K3: Sales so far | L3: Cost per sale so far | M3: Stop rule check | N3: What you changed or noticed
H4: =IF(OR(B4="",N(D4)=0),"",B4/D4) | I4: =IF(OR(D4="",N(C4)=0),"",D4/C4) | J4: =IF(B4="","",SUM(B$4:B4)) | K4: =IF(B4="","",SUM(F$4:F4)) | L4: =IF(OR(J4="",N(K4)=0),"",J4/K4) | M4: =IF(B4="","",IF(AND(J4>=2*N('Plan'!$B$18),N(K4)=0,N('Plan'!$B$18)>0),"STOP: two sales worth spent, zero sales",IF(AND(N('Plan'!$B$14)>0,J4>=N('Plan'!$B$14)),IF(AND(N(K4)>0,L4<N('Plan'!$B$26)),"Cap reached. It worked: confirm with a second test","Cap reached. Stop and review"),IF(AND(N(K4)>0,L4<N('Plan'!$B$26)),"On track","Keep going, watch the numbers"))))
H5: =IF(OR(B5="",N(D5)=0),"",B5/D5) | I5: =IF(OR(D5="",N(C5)=0),"",D5/C5) | J5: =IF(B5="","",SUM(B$4:B5)) | K5: =IF(B5="","",SUM(F$4:F5)) | L5: =IF(OR(J5="",N(K5)=0),"",J5/K5) | M5: =IF(B5="","",IF(AND(J5>=2*N('Plan'!$B$18),N(K5)=0,N('Plan'!$B$18)>0),"STOP: two sales worth spent, zero sales",IF(AND(N('Plan'!$B$14)>0,J5>=N('Plan'!$B$14)),IF(AND(N(K5)>0,L5<N('Plan'!$B$26)),"Cap reached. It worked: confirm with a second test","Cap reached. Stop and review"),IF(AND(N(K5)>0,L5<N('Plan'!$B$26)),"On track","Keep going, watch the numbers"))))
H6: =IF(OR(B6="",N(D6)=0),"",B6/D6) | I6: =IF(OR(D6="",N(C6)=0),"",D6/C6) | J6: =IF(B6="","",SUM(B$4:B6)) | K6: =IF(B6="","",SUM(F$4:F6)) | L6: =IF(OR(J6="",N(K6)=0),"",J6/K6) | M6: =IF(B6="","",IF(AND(J6>=2*N('Plan'!$B$18),N(K6)=0,N('Plan'!$B$18)>0),"STOP: two sales worth spent, zero sales",IF(AND(N('Plan'!$B$14)>0,J6>=N('Plan'!$B$14)),IF(AND(N(K6)>0,L6<N('Plan'!$B$26)),"Cap reached. It worked: confirm with a second test","Cap reached. Stop and review"),IF(AND(N(K6)>0,L6<N('Plan'!$B$26)),"On track","Keep going, watch the numbers"))))
H7: =IF(OR(B7="",N(D7)=0),"",B7/D7) | I7: =IF(OR(D7="",N(C7)=0),"",D7/C7) | J7: =IF(B7="","",SUM(B$4:B7)) | K7: =IF(B7="","",SUM(F$4:F7)) | L7: =IF(OR(J7="",N(K7)=0),"",J7/K7) | M7: =IF(B7="","",IF(AND(J7>=2*N('Plan'!$B$18),N(K7)=0,N('Plan'!$B$18)>0),"STOP: two sales worth spent, zero sales",IF(AND(N('Plan'!$B$14)>0,J7>=N('Plan'!$B$14)),IF(AND(N(K7)>0,L7<N('Plan'!$B$26)),"Cap reached. It worked: confirm with a second test","Cap reached. Stop and review"),IF(AND(N(K7)>0,L7<N('Plan'!$B$26)),"On track","Keep going, watch the numbers"))))
H8: =IF(OR(B8="",N(D8)=0),"",B8/D8) | I8: =IF(OR(D8="",N(C8)=0),"",D8/C8) | J8: =IF(B8="","",SUM(B$4:B8)) | K8: =IF(B8="","",SUM(F$4:F8)) | L8: =IF(OR(J8="",N(K8)=0),"",J8/K8) | M8: =IF(B8="","",IF(AND(J8>=2*N('Plan'!$B$18),N(K8)=0,N('Plan'!$B$18)>0),"STOP: two sales worth spent, zero sales",IF(AND(N('Plan'!$B$14)>0,J8>=N('Plan'!$B$14)),IF(AND(N(K8)>0,L8<N('Plan'!$B$26)),"Cap reached. It worked: confirm with a second test","Cap reached. Stop and review"),IF(AND(N(K8)>0,L8<N('Plan'!$B$26)),"On track","Keep going, watch the numbers"))))
H9: =IF(OR(B9="",N(D9)=0),"",B9/D9) | I9: =IF(OR(D9="",N(C9)=0),"",D9/C9) | J9: =IF(B9="","",SUM(B$4:B9)) | K9: =IF(B9="","",SUM(F$4:F9)) | L9: =IF(OR(J9="",N(K9)=0),"",J9/K9) | M9: =IF(B9="","",IF(AND(J9>=2*N('Plan'!$B$18),N(K9)=0,N('Plan'!$B$18)>0),"STOP: two sales worth spent, zero sales",IF(AND(N('Plan'!$B$14)>0,J9>=N('Plan'!$B$14)),IF(AND(N(K9)>0,L9<N('Plan'!$B$26)),"Cap reached. It worked: confirm with a second test","Cap reached. Stop and review"),IF(AND(N(K9)>0,L9<N('Plan'!$B$26)),"On track","Keep going, watch the numbers"))))
H10: =IF(OR(B10="",N(D10)=0),"",B10/D10) | I10: =IF(OR(D10="",N(C10)=0),"",D10/C10) | J10: =IF(B10="","",SUM(B$4:B10)) | K10: =IF(B10="","",SUM(F$4:F10)) | L10: =IF(OR(J10="",N(K10)=0),"",J10/K10) | M10: =IF(B10="","",IF(AND(J10>=2*N('Plan'!$B$18),N(K10)=0,N('Plan'!$B$18)>0),"STOP: two sales worth spent, zero sales",IF(AND(N('Plan'!$B$14)>0,J10>=N('Plan'!$B$14)),IF(AND(N(K10)>0,L10<N('Plan'!$B$26)),"Cap reached. It worked: confirm with a second test","Cap reached. Stop and review"),IF(AND(N(K10)>0,L10<N('Plan'!$B$26)),"On track","Keep going, watch the numbers"))))
H11: =IF(OR(B11="",N(D11)=0),"",B11/D11) | I11: =IF(OR(D11="",N(C11)=0),"",D11/C11) | J11: =IF(B11="","",SUM(B$4:B11)) | K11: =IF(B11="","",SUM(F$4:F11)) | L11: =IF(OR(J11="",N(K11)=0),"",J11/K11) | M11: =IF(B11="","",IF(AND(J11>=2*N('Plan'!$B$18),N(K11)=0,N('Plan'!$B$18)>0),"STOP: two sales worth spent, zero sales",IF(AND(N('Plan'!$B$14)>0,J11>=N('Plan'!$B$14)),IF(AND(N(K11)>0,L11<N('Plan'!$B$26)),"Cap reached. It worked: confirm with a second test","Cap reached. Stop and review"),IF(AND(N(K11)>0,L11<N('Plan'!$B$26)),"On track","Keep going, watch the numbers"))))
H12: =IF(OR(B12="",N(D12)=0),"",B12/D12) | I12: =IF(OR(D12="",N(C12)=0),"",D12/C12) | J12: =IF(B12="","",SUM(B$4:B12)) | K12: =IF(B12="","",SUM(F$4:F12)) | L12: =IF(OR(J12="",N(K12)=0),"",J12/K12) | M12: =IF(B12="","",IF(AND(J12>=2*N('Plan'!$B$18),N(K12)=0,N('Plan'!$B$18)>0),"STOP: two sales worth spent, zero sales",IF(AND(N('Plan'!$B$14)>0,J12>=N('Plan'!$B$14)),IF(AND(N(K12)>0,L12<N('Plan'!$B$26)),"Cap reached. It worked: confirm with a second test","Cap reached. Stop and review"),IF(AND(N(K12)>0,L12<N('Plan'!$B$26)),"On track","Keep going, watch the numbers"))))
H13: =IF(OR(B13="",N(D13)=0),"",B13/D13) | I13: =IF(OR(D13="",N(C13)=0),"",D13/C13) | J13: =IF(B13="","",SUM(B$4:B13)) | K13: =IF(B13="","",SUM(F$4:F13)) | L13: =IF(OR(J13="",N(K13)=0),"",J13/K13) | M13: =IF(B13="","",IF(AND(J13>=2*N('Plan'!$B$18),N(K13)=0,N('Plan'!$B$18)>0),"STOP: two sales worth spent, zero sales",IF(AND(N('Plan'!$B$14)>0,J13>=N('Plan'!$B$14)),IF(AND(N(K13)>0,L13<N('Plan'!$B$26)),"Cap reached. It worked: confirm with a second test","Cap reached. Stop and review"),IF(AND(N(K13)>0,L13<N('Plan'!$B$26)),"On track","Keep going, watch the numbers"))))
H14: =IF(OR(B14="",N(D14)=0),"",B14/D14) | I14: =IF(OR(D14="",N(C14)=0),"",D14/C14) | J14: =IF(B14="","",SUM(B$4:B14)) | K14: =IF(B14="","",SUM(F$4:F14)) | L14: =IF(OR(J14="",N(K14)=0),"",J14/K14) | M14: =IF(B14="","",IF(AND(J14>=2*N('Plan'!$B$18),N(K14)=0,N('Plan'!$B$18)>0),"STOP: two sales worth spent, zero sales",IF(AND(N('Plan'!$B$14)>0,J14>=N('Plan'!$B$14)),IF(AND(N(K14)>0,L14<N('Plan'!$B$26)),"Cap reached. It worked: confirm with a second test","Cap reached. Stop and review"),IF(AND(N(K14)>0,L14<N('Plan'!$B$26)),"On track","Keep going, watch the numbers"))))
H15: =IF(OR(B15="",N(D15)=0),"",B15/D15) | I15: =IF(OR(D15="",N(C15)=0),"",D15/C15) | J15: =IF(B15="","",SUM(B$4:B15)) | K15: =IF(B15="","",SUM(F$4:F15)) | L15: =IF(OR(J15="",N(K15)=0),"",J15/K15) | M15: =IF(B15="","",IF(AND(J15>=2*N('Plan'!$B$18),N(K15)=0,N('Plan'!$B$18)>0),"STOP: two sales worth spent, zero sales",IF(AND(N('Plan'!$B$14)>0,J15>=N('Plan'!$B$14)),IF(AND(N(K15)>0,L15<N('Plan'!$B$26)),"Cap reached. It worked: confirm with a second test","Cap reached. Stop and review"),IF(AND(N(K15)>0,L15<N('Plan'!$B$26)),"On track","Keep going, watch the numbers"))))
... H33: =IF(OR(B33="",N(D33)=0),"",B33/D33) | I33: =IF(OR(D33="",N(C33)=0),"",D33/C33) | J33: =IF(B33="","",SUM(B$4:B33)) | K33: =IF(B33="","",SUM(F$4:F33)) | L33: =IF(OR(J33="",N(K33)=0),"",J33/K33) | M33: =IF(B33="","",IF(AND(J33>=2*N('Plan'!$B$18),N(K33)=0,N('Plan'!$B$18)>0),"STOP: two sales worth spent, zero sales",IF(AND(N('Plan'!$B$14)>0,J33>=N('Plan'!$B$14)),IF(AND(N(K33)>0,L33<N('Plan'!$B$26)),"Cap reached. It worked: confirm with a second test","Cap reached. Stop and review"),IF(AND(N(K33)>0,L33<N('Plan'!$B$26)),"On track","Keep going, watch the numbers"))))

Sheet Results
A1: What the test taught you
A2: Stopping is not failing. A stopped test with clear notes beats a lucky one you can't explain.
A4: TOTALS
A5: Spent ($) | B5: =SUM('Daily log'!$B$4:$B$33)
A6: Clicks | B6: =SUM('Daily log'!$D$4:$D$33)
A7: Average cost per click ($) | B7: =IF($B$6=0,"",$B$5/$B$6)
A8: Page visits | B8: =SUM('Daily log'!$E$4:$E$33)
A9: Sales | B9: =SUM('Daily log'!$F$4:$F$33)
A10: Page conversion (sales / visits) | B10: =IF($B$8=0,"",$B$9/$B$8)
A11: Cost per sale ($) | B11: =IF($B$9=0,"",$B$5/$B$9)
A12: What one sale earns you ($) | B12: =N('Plan'!$B$26)
A13: Read | B13: =IF($B$5=0,"Log your first day.",IF($B$9=0,"No sales yet. If you have spent two sales worth, pause and change one thing.",IF($B$11<N('Plan'!$B$26),"Each sale cost less than it earns. Confirm with a second test before you raise the budget, then raise it in small steps.","Each sale cost more than it earns. Change one thing: the hook, the audience, the headline or the offer.")))
A15: YOUR NOTES
A16: What you learned (cost per click, conversion, top comment or objection)
A17: The one change for the next test
